cycle_detector
